.gitignore
CHANGES.rst
MANIFEST.in
README.rst
Vagrantfile
settings.py.example
setup.py
custom/README.txt
docs/Makefile
docs/source/bash.rst
docs/source/commands.rst
docs/source/conf.py
docs/source/development.rst
docs/source/github.rst
docs/source/index.rst
docs/source/jenkins.rst
docs/source/osx.rst
docs/source/python.rst
docs/source/subversion.rst
docs/source/troubleshooting.rst
docs/source/ubuntu.rst
docs/source/vagrant.rst
docs/source/webhooks.rst
docs/source/zabbix.rst
docs/source/zapier.rst
docs/source/_static/sevabot-32.png
docs/source/images/admin.png
docs/source/images/authorize.png
docs/source/images/avatar.png
docs/source/images/demo.png
docs/source/images/invite.png
docs/source/images/sad.png
docs/source/images/settings.png
docs/source/images/sevabot-24.png
docs/source/images/sevabot-256.png
docs/source/images/sevabot-32.png
docs/source/images/sevabot-64.png
docs/source/images/sevabot-logo.svg
docs/source/images/skype-login.png
docs/source/images/vnc.png
docs/source/images/zabbix-item.png
docs/source/images/zabbix-trigger.png
docs/source/images/zapier.png
examples/ci-loop.bash
examples/send.sh
examples/send2.sh
examples/svn-post-commit.sh
logs/README.txt
modules/call.py
modules/dice.py
modules/memoryhog.sh
modules/ping.sh
modules/sad.py
modules/soundcloud.rb
modules/tasks.py
modules/timeout.sh
modules/weather.py
puppet/manifests/site.pp
scripts/check-service.sh
scripts/reboot-seva.sh
scripts/start-server.sh
scripts/start-vnc.sh
sevabot/__init__.py
sevabot/utils.py
sevabot.egg-info/PKG-INFO
sevabot.egg-info/SOURCES.txt
sevabot.egg-info/dependency_links.txt
sevabot.egg-info/entry_points.txt
sevabot.egg-info/requires.txt
sevabot.egg-info/top_level.txt
sevabot/bot/__init__.py
sevabot/bot/bot.py
sevabot/bot/handlers.py
sevabot/bot/modules.py
sevabot/bot/stateful.py
sevabot/frontend/__init__.py
sevabot/frontend/api.py
sevabot/frontend/daemon.py
sevabot/frontend/main.py
sevabot/frontend/static/favicon.ico
sevabot/frontend/static/seva.css
sevabot/frontend/templates/chat_message.html
sevabot/frontend/templates/chats.html
sevabot/frontend/templates/index.html