Metadata-Version: 1.0
Name: sevabot
Version: 1.2.3
Summary: A Skype bot supporting integration with external services
Home-page: https://github.com/opensourcehacker/sevabot
Author: Mikko Ohtamaa
Author-email: mikko@opensourcehacker.com
License: BSD
Platform: UNKNOWN
Classifier: Programming Language :: Python
